conformity/__init__.py
conformity/base.py
conformity/classifier.py
conformity/metrics.py
conformity/regressor.py
conformity_calib-0.1.0.dist-info/METADATA
conformity_calib-0.1.0.dist-info/WHEEL
conformity_calib-0.1.0.dist-info/RECORD
