Metadata-Version: 2.4
Name: conformity-calib
Version: 0.1.0
Summary: Add your description here
Author-email: Jack <jackg18@hotmail.co.uk>
Requires-Python: >=3.9
Requires-Dist: numpy>=2.0.2
Requires-Dist: scikit-learn>=1.6.1
Requires-Dist: typing-extensions>=4.15.0
